chafer/__init__.py
chafer/ch_art_suppr_tools.py
chafer/predict_charge_centers.py
chafer-0.4.dist-info/LICENSE
chafer-0.4.dist-info/METADATA
chafer-0.4.dist-info/WHEEL
chafer-0.4.dist-info/top_level.txt
chafer-0.4.dist-info/RECORD
