Metadata-Version: 2.1
Name: chafer
Version: 0.4
Summary: CHArge artiFact supprEssion tool for scanning electRon microscope images
Home-page: https://github.com/rosalindfranklininstitute/chafer
Author: Luis Perdigao
Author-email: luis.perdigao@rfi.ac.uk
License: Apache License, Version 2.0
Classifier: Development Status :: 4 - Beta 
Classifier: License :: OSI Approved :: Apache Software License
Classifier: Natural Language :: English
Classifier: Programming Language :: Python :: 3.8
Classifier: Operating System :: Microsoft :: Windows
Classifier: Operating System :: MacOS
Classifier: Operating System :: POSIX :: Linux
Classifier: Topic :: Scientific/Engineering :: Image Processing
License-File: LICENSE
Requires-Dist: numpy
Requires-Dist: scipy
Requires-Dist: scikit-image
